{"meta_data":{"additional_headers":{},"game_name":"VisionGame","version":"0.3.3","user_name":"STs1003","device_id":"3C611A35-F3E5-425C-9AB3-EF8FC69DAC7D","session_number":5},"data":[{"game_type":"Contour","element":0,"run":0,"contour_mode":"ContourPreTest","contour_class":"Circle_General","contour_regen":"None","contour_parameter":"OrientationJitter","time":1551895390393.59},{"game_type":"Contour","element":0,"run":1,"contour_mode":"ContourPreTest","contour_class":"Circle_General","contour_regen":"None","contour_parameter":"Count","time":1551895516859.93},{"game_type":"Contour","element":0,"run":2,"contour_mode":"ContourTask","contour_class":"Blob_10","contour_regen":"None","contour_parameter":"OrientationJitter","time":1551895652393.47},{"game_type":"Contour","element":0,"run":3,"contour_mode":"ContourTask","contour_class":"Blob_10","contour_regen":"None","contour_parameter":"Count","time":1551895777249.96},{"game_type":"Contour","element":0,"run":4,"contour_mode":"ContourTask","contour_class":"Spiral_General","contour_regen":"None","contour_parameter":"OrientationJitter","time":1551895902730.45},{"game_type":"Contour","element":0,"run":5,"contour_mode":"ContourTask","contour_class":"Spiral_General","contour_regen":"None","contour_parameter":"Count","time":1551896028546.3},{"game_type":"Contour","element":0,"run":6,"contour_mode":"ContourTask","contour_class":"Blob_10","contour_regen":"None","contour_parameter":"OrientationJitter","time":1551896154774.42},{"game_type":"Contour","element":0,"run":7,"contour_mode":"ContourTask","contour_class":"Blob_10","contour_regen":"None","contour_parameter":"Count","time":1551896278914.25},{"game_type":"Contour","element":0,"run":8,"contour_mode":"ContourTask","contour_class":"Squiggle_H_Roving","contour_regen":"None","contour_parameter":"OrientationJitter","time":1551896403945.54},{"game_type":"Contour","element":0,"run":9,"contour_mode":"ContourPostTest","contour_class":"Squiggle_V_Roving","contour_regen":"None","contour_parameter":"OrientationJitter","time":1551896544650.25},{"game_type":"Contour","element":2,"run":0,"contour_mode":"ContourPreTest","contour_class":"Circle_General","contour_regen":"None","contour_parameter":"OrientationJitter","time":1551896765880.1},{"game_type":"Contour","element":2,"run":1,"contour_mode":"ContourPreTest","contour_class":"Circle_General","contour_regen":"None","contour_parameter":"Count","time":1551896898172.89},{"game_type":"Contour","element":2,"run":2,"contour_mode":"ContourTask","contour_class":"Blob_10","contour_regen":"None","contour_parameter":"OrientationJitter","time":1551897023923.54},{"game_type":"Contour","element":2,"run":3,"contour_mode":"ContourTask","contour_class":"Blob_10","contour_regen":"None","contour_parameter":"Count","time":1551897148317.09},{"game_type":"Contour","element":2,"run":4,"contour_mode":"ContourTask","contour_class":"Spiral_General","contour_regen":"None","contour_parameter":"OrientationJitter","time":1551897272711.58},{"game_type":"Contour","element":2,"run":5,"contour_mode":"ContourTask","contour_class":"Spiral_General","contour_regen":"None","contour_parameter":"Count","time":1551897404378.25},{"game_type":"Contour","element":2,"run":6,"contour_mode":"ContourTask","contour_class":"Blob_10","contour_regen":"None","contour_parameter":"OrientationJitter","time":1551897528246.66},{"game_type":"Contour","element":2,"run":7,"contour_mode":"ContourTask","contour_class":"Blob_10","contour_regen":"None","contour_parameter":"Count","time":1551897660787.85},{"game_type":"Contour","element":2,"run":8,"contour_mode":"ContourPostTest","contour_class":"Ellipse_R_Fixed","contour_regen":"Orientation","contour_parameter":"OrientationJitter","time":1551897786619.97},{"game_type":"Score","game_mode":"Contour","medal":"Gold","level":5,"score":22,"time":1551897920786.02}]}