{"meta_data":{"additional_headers":{},"game_name":"VisionGame","version":"0.3.3","user_name":"STS1018","device_id":"F9FD343D-A5AA-4074-86D3-45276E67CFB9","session_number":5},"data":[{"trial":0,"type":"Target","inducers":16,"orientationJitter":0,"spatialJitter":0,"x":1948,"y":760,"w":652,"h":652,"spawn_time":1550708287385.71},{"trial":1,"type":"Target","inducers":16,"orientationJitter":0,"spatialJitter":0,"x":1192,"y":220,"w":652,"h":652,"spawn_time":1550708290404.92},{"trial":2,"type":"Target","inducers":16,"orientationJitter":0,"spatialJitter":0,"x":536,"y":440,"w":652,"h":652,"spawn_time":1550708295639.96},{"trial":3,"type":"Target","inducers":16,"orientationJitter":0.02222222,"spatialJitter":0,"x":1724,"y":748,"w":652,"h":652,"spawn_time":1550708299636.33},{"trial":4,"type":"Target","inducers":16,"orientationJitter":0.02222222,"spatialJitter":0,"x":152,"y":892,"w":652,"h":652,"spawn_time":1550708307179.38},{"trial":5,"type":"Target","inducers":16,"orientationJitter":0.02222222,"spatialJitter":0,"x":1092,"y":816,"w":652,"h":652,"spawn_time":1550708314951.21},{"trial":6,"type":"Target","inducers":16,"orientationJitter":0,"spatialJitter":0,"x":108,"y":960,"w":652,"h":652,"spawn_time":1550708325963.24},{"trial":7,"type":"Target","inducers":16,"orientationJitter":0,"spatialJitter":0,"x":100,"y":952,"w":652,"h":652,"spawn_time":1550708336979.01},{"trial":8,"type":"Target","inducers":16,"orientationJitter":0,"spatialJitter":0,"x":1460,"y":444,"w":652,"h":652,"spawn_time":1550708344323.13},{"trial":9,"type":"Target","inducers":16,"orientationJitter":0,"spatialJitter":0,"x":52,"y":1128,"w":652,"h":652,"spawn_time":1550708355335.32},{"trial":10,"type":"Target","inducers":16,"orientationJitter":0,"spatialJitter":0,"x":1136,"y":884,"w":652,"h":652,"spawn_time":1550708361664.81},{"trial":11,"type":"Target","inducers":16,"orientationJitter":0,"spatialJitter":0,"x":520,"y":1040,"w":652,"h":652,"spawn_time":1550708369360.96},{"trial":12,"type":"Target","inducers":16,"orientationJitter":0,"spatialJitter":0,"x":1676,"y":1272,"w":652,"h":652,"spawn_time":1550708371838.9},{"trial":13,"type":"Target","inducers":16,"orientationJitter":0.01111111,"spatialJitter":0,"x":172,"y":112,"w":652,"h":652,"spawn_time":1550708378157.01},{"trial":14,"type":"Target","inducers":16,"orientationJitter":0.01111111,"spatialJitter":0,"x":560,"y":140,"w":652,"h":652,"spawn_time":1550708385300.72},{"trial":15,"type":"Target","inducers":16,"orientationJitter":0.01111111,"spatialJitter":0,"x":428,"y":780,"w":652,"h":652,"spawn_time":1550708393781.22},{"trial":16,"type":"Target","inducers":16,"orientationJitter":0.01111111,"spatialJitter":0,"x":1584,"y":884,"w":652,"h":652,"spawn_time":1550708396520.28},{"trial":17,"type":"Target","inducers":16,"orientationJitter":0.01111111,"spatialJitter":0,"x":596,"y":220,"w":652,"h":652,"spawn_time":1550708402538.96},{"trial":18,"type":"Target","inducers":16,"orientationJitter":0.02222222,"spatialJitter":0,"x":1016,"y":280,"w":652,"h":652,"spawn_time":1550708404769.6},{"trial":19,"type":"Target","inducers":16,"orientationJitter":0.02222222,"spatialJitter":0,"x":76,"y":368,"w":652,"h":652,"spawn_time":1550708406977.76}]}