{
  "meta_data": {
    "additional_headers": {},
    "game_name": "VisionGame",
    "version": "0.7.2",
    "user_name": "CA1006D",
    "organization": "braingamecenter",
    "study": "RA_2018_10",
    "session_number": 7,
    "device_id": "D0B975EF-9219-4004-B2D3-7B19359FA20F"
  },
  "data": [
    {
      "trial": 0,
      "type": "Target",
      "inducers": 20,
      "orientationJitter": 0,
      "spatialJitter": 0,
      "x": 1308,
      "y": 952,
      "w": 820,
      "h": 820,
      "spawn_time": 1572549933264.93
    },
    {
      "trial": 1,
      "type": "Target",
      "inducers": 20,
      "orientationJitter": 0,
      "spatialJitter": 0,
      "x": 264,
      "y": 372,
      "w": 820,
      "h": 820,
      "spawn_time": 1572549944299.54
    },
    {
      "trial": 2,
      "type": "Target",
      "inducers": 20,
      "orientationJitter": 0,
      "spatialJitter": 0,
      "x": 1308,
      "y": 732,
      "w": 820,
      "h": 820,
      "spawn_time": 1572549953867.98
    },
    {
      "trial": 3,
      "type": "Target",
      "inducers": 20,
      "orientationJitter": 0,
      "spatialJitter": 0,
      "x": 1044,
      "y": 80,
      "w": 820,
      "h": 820,
      "spawn_time": 1572549957492.43
    },
    {
      "trial": 4,
      "type": "Target",
      "inducers": 20,
      "orientationJitter": 0,
      "spatialJitter": 0,
      "x": 340,
      "y": 956,
      "w": 820,
      "h": 820,
      "spawn_time": 1572549961299.26
    },
    {
      "trial": 5,
      "type": "Target",
      "inducers": 20,
      "orientationJitter": 0,
      "spatialJitter": 0,
      "x": 1072,
      "y": 372,
      "w": 820,
      "h": 820,
      "spawn_time": 1572549965009.29
    },
    {
      "trial": 6,
      "type": "Target",
      "inducers": 20,
      "orientationJitter": 0,
      "spatialJitter": 0,
      "x": 928,
      "y": 584,
      "w": 820,
      "h": 820,
      "spawn_time": 1572549972607.98
    },
    {
      "trial": 7,
      "type": "Target",
      "inducers": 20,
      "orientationJitter": 0,
      "spatialJitter": 0,
      "x": 492,
      "y": 416,
      "w": 820,
      "h": 820,
      "spawn_time": 1572549975569.68
    },
    {
      "trial": 8,
      "type": "Target",
      "inducers": 20,
      "orientationJitter": 0,
      "spatialJitter": 0,
      "x": 228,
      "y": 100,
      "w": 820,
      "h": 820,
      "spawn_time": 1572549979737.97
    },
    {
      "trial": 9,
      "type": "Target",
      "inducers": 20,
      "orientationJitter": 0,
      "spatialJitter": 0,
      "x": 800,
      "y": 988,
      "w": 820,
      "h": 820,
      "spawn_time": 1572549982798.2
    },
    {
      "trial": 10,
      "type": "Target",
      "inducers": 20,
      "orientationJitter": 0,
      "spatialJitter": 0,
      "x": 248,
      "y": 388,
      "w": 820,
      "h": 820,
      "spawn_time": 1572549986082.48
    },
    {
      "trial": 11,
      "type": "Target",
      "inducers": 20,
      "orientationJitter": 0,
      "spatialJitter": 0,
      "x": 1148,
      "y": 920,
      "w": 820,
      "h": 820,
      "spawn_time": 1572549988581.01
    },
    {
      "trial": 12,
      "type": "Target",
      "inducers": 20,
      "orientationJitter": 0,
      "spatialJitter": 0,
      "x": 1320,
      "y": 212,
      "w": 820,
      "h": 820,
      "spawn_time": 1572549990750.28
    },
    {
      "trial": 13,
      "type": "Target",
      "inducers": 20,
      "orientationJitter": 0,
      "spatialJitter": 0,
      "x": 1700,
      "y": 128,
      "w": 820,
      "h": 820,
      "spawn_time": 1572549993007.54
    },
    {
      "trial": 14,
      "type": "Target",
      "inducers": 20,
      "orientationJitter": 0,
      "spatialJitter": 0,
      "x": 896,
      "y": 968,
      "w": 820,
      "h": 820,
      "spawn_time": 1572549996768.93
    },
    {
      "trial": 15,
      "type": "Target",
      "inducers": 20,
      "orientationJitter": 0,
      "spatialJitter": 0,
      "x": 588,
      "y": 144,
      "w": 820,
      "h": 820,
      "spawn_time": 1572550000929.55
    },
    {
      "trial": 16,
      "type": "Target",
      "inducers": 20,
      "orientationJitter": 0,
      "spatialJitter": 0,
      "x": 1376,
      "y": 116,
      "w": 820,
      "h": 820,
      "spawn_time": 1572550011230.71
    },
    {
      "trial": 17,
      "type": "Target",
      "inducers": 20,
      "orientationJitter": 0,
      "spatialJitter": 0,
      "x": 800,
      "y": 548,
      "w": 820,
      "h": 820,
      "spawn_time": 1572550015869.41
    },
    {
      "trial": 18,
      "type": "Target",
      "inducers": 20,
      "orientationJitter": 0,
      "spatialJitter": 0,
      "x": 1536,
      "y": 252,
      "w": 820,
      "h": 820,
      "spawn_time": 1572550021738.33
    },
    {
      "trial": 19,
      "type": "Target",
      "inducers": 20,
      "orientationJitter": 0,
      "spatialJitter": 0,
      "x": 1300,
      "y": 716,
      "w": 820,
      "h": 820,
      "spawn_time": 1572550026528.58
    },
    {
      "trial": 20,
      "type": "Target",
      "inducers": 20,
      "orientationJitter": 0,
      "spatialJitter": 0,
      "x": 460,
      "y": 1056,
      "w": 820,
      "h": 820,
      "spawn_time": 1572550030334.07
    },
    {
      "trial": 21,
      "type": "Target",
      "inducers": 20,
      "orientationJitter": 0,
      "spatialJitter": 0,
      "x": 1124,
      "y": 752,
      "w": 820,
      "h": 820,
      "spawn_time": 1572550036191.09
    },
    {
      "trial": 22,
      "type": "Target",
      "inducers": 20,
      "orientationJitter": 0,
      "spatialJitter": 0,
      "x": 1164,
      "y": 452,
      "w": 820,
      "h": 820,
      "spawn_time": 1572550040862.55
    },
    {
      "trial": 23,
      "type": "Target",
      "inducers": 20,
      "orientationJitter": 0,
      "spatialJitter": 0,
      "x": 76,
      "y": 552,
      "w": 820,
      "h": 820,
      "spawn_time": 1572550044522.81
    },
    {
      "trial": 24,
      "type": "Target",
      "inducers": 20,
      "orientationJitter": 0,
      "spatialJitter": 0,
      "x": 1348,
      "y": 1008,
      "w": 820,
      "h": 820,
      "spawn_time": 1572550049322.8
    },
    {
      "trial": 25,
      "type": "Target",
      "inducers": 20,
      "orientationJitter": 0,
      "spatialJitter": 0,
      "x": 1624,
      "y": 808,
      "w": 820,
      "h": 820,
      "spawn_time": 1572550050709.08
    },
    {
      "trial": 26,
      "type": "Target",
      "inducers": 20,
      "orientationJitter": 0,
      "spatialJitter": 0,
      "x": 524,
      "y": 92,
      "w": 820,
      "h": 820,
      "spawn_time": 1572550051943.58
    }
  ]
}