{"meta_data":{"additional_headers":{},"game_name":"VisionGame","version":"0.5.0","user_name":"Na1005a","organization":"braingamecenter","study":"RA_2018_10","session_number":17,"device_id":"7F8D1EFC-29CC-4237-8B4A-571EBB00CE9A"},"data":[{"trial":0,"type":"Target","inducers":16,"orientationJitter":0,"spatialJitter":0,"x":1064,"y":376,"w":484,"h":612,"spawn_time":1555011833482.64},{"trial":1,"type":"Target","inducers":16,"orientationJitter":0,"spatialJitter":0,"x":652,"y":1076,"w":388,"h":652,"spawn_time":1555011835603.32},{"trial":2,"type":"Target","inducers":16,"orientationJitter":0,"spatialJitter":0,"x":804,"y":572,"w":548,"h":556,"spawn_time":1555011837469},{"trial":3,"type":"Target","inducers":16,"orientationJitter":0,"spatialJitter":0,"x":688,"y":396,"w":652,"h":380,"spawn_time":1555011839285.76},{"trial":4,"type":"Target","inducers":16,"orientationJitter":0,"spatialJitter":0,"x":1816,"y":1412,"w":652,"h":388,"spawn_time":1555011841337.63},{"trial":5,"type":"Target","inducers":16,"orientationJitter":0,"spatialJitter":0,"x":436,"y":484,"w":572,"h":532,"spawn_time":1555011843069.85},{"trial":6,"type":"Target","inducers":16,"orientationJitter":0,"spatialJitter":0,"x":2004,"y":756,"w":356,"h":652,"spawn_time":1555011845088.38},{"trial":7,"type":"Target","inducers":16,"orientationJitter":0,"spatialJitter":0,"x":1176,"y":1252,"w":652,"h":348,"spawn_time":1555011846837.11},{"trial":8,"type":"Target","inducers":16,"orientationJitter":0,"spatialJitter":0,"x":192,"y":324,"w":604,"h":492,"spawn_time":1555011848789.32},{"trial":9,"type":"Target","inducers":16,"orientationJitter":0,"spatialJitter":0,"x":852,"y":1072,"w":636,"h":436,"spawn_time":1555011850923.02},{"trial":10,"type":"Target","inducers":16,"orientationJitter":0,"spatialJitter":0,"x":264,"y":764,"w":396,"h":644,"spawn_time":1555011853081.34},{"trial":11,"type":"Target","inducers":16,"orientationJitter":0,"spatialJitter":0,"x":1852,"y":752,"w":636,"h":420,"spawn_time":1555011855065.28},{"trial":12,"type":"Target","inducers":16,"orientationJitter":0,"spatialJitter":0,"x":1624,"y":368,"w":612,"h":484,"spawn_time":1555011856965.72},{"trial":13,"type":"Target","inducers":16,"orientationJitter":0,"spatialJitter":0,"x":1460,"y":1044,"w":588,"h":516,"spawn_time":1555011858172.97},{"trial":14,"type":"Target","inducers":16,"orientationJitter":0,"spatialJitter":0,"x":544,"y":192,"w":548,"h":556,"spawn_time":1555011859356.2},{"trial":15,"type":"Target","inducers":16,"orientationJitter":0,"spatialJitter":0,"x":1564,"y":484,"w":652,"h":348,"spawn_time":1555011860731.69},{"trial":16,"type":"Target","inducers":16,"orientationJitter":0,"spatialJitter":0,"x":1444,"y":344,"w":348,"h":652,"spawn_time":1555011862006.72},{"trial":17,"type":"Target","inducers":16,"orientationJitter":0,"spatialJitter":0,"x":1960,"y":1100,"w":636,"h":420,"spawn_time":1555011863382.21},{"trial":18,"type":"Target","inducers":16,"orientationJitter":0,"spatialJitter":0,"x":280,"y":540,"w":620,"h":468,"spawn_time":1555011865425.61},{"trial":19,"type":"Target","inducers":16,"orientationJitter":0,"spatialJitter":0,"x":584,"y":100,"w":436,"h":636,"spawn_time":1555011867745.72},{"trial":20,"type":"Target","inducers":16,"orientationJitter":0,"spatialJitter":0,"x":1800,"y":316,"w":652,"h":356,"spawn_time":1555011869910.1},{"trial":21,"type":"Target","inducers":16,"orientationJitter":0,"spatialJitter":0,"x":660,"y":332,"w":652,"h":356,"spawn_time":1555011872271.34},{"trial":22,"type":"Target","inducers":16,"orientationJitter":0,"spatialJitter":0,"x":952,"y":1108,"w":412,"h":644,"spawn_time":1555011874335.99},{"trial":23,"type":"Target","inducers":16,"orientationJitter":0,"spatialJitter":0,"x":432,"y":876,"w":500,"h":596,"spawn_time":1555011876773.54},{"trial":24,"type":"Target","inducers":16,"orientationJitter":0.01111111,"spatialJitter":0,"x":1476,"y":652,"w":548,"h":564,"spawn_time":1555011878878.59},{"trial":25,"type":"Target","inducers":16,"orientationJitter":0.01111111,"spatialJitter":0,"x":1092,"y":552,"w":388,"h":652,"spawn_time":1555011880911.85},{"trial":26,"type":"Target","inducers":16,"orientationJitter":0.01111111,"spatialJitter":0,"x":712,"y":732,"w":596,"h":500,"spawn_time":1555011882937.6},{"trial":27,"type":"Target","inducers":16,"orientationJitter":0.02222222,"spatialJitter":0,"x":164,"y":936,"w":532,"h":580,"spawn_time":1555011884937.98},{"trial":28,"type":"Target","inducers":16,"orientationJitter":0.01111111,"spatialJitter":0,"x":1932,"y":500,"w":364,"h":652,"spawn_time":1555011887055.1},{"trial":29,"type":"Target","inducers":16,"orientationJitter":0.01111111,"spatialJitter":0,"x":176,"y":728,"w":532,"h":580,"spawn_time":1555011889667.3},{"trial":30,"type":"Target","inducers":16,"orientationJitter":0.01111111,"spatialJitter":0,"x":1020,"y":1196,"w":532,"h":580,"spawn_time":1555011892166.93},{"trial":31,"type":"Target","inducers":16,"orientationJitter":0.02222222,"spatialJitter":0,"x":620,"y":1088,"w":396,"h":644,"spawn_time":1555011894331.22},{"trial":32,"type":"Target","inducers":16,"orientationJitter":0.02222222,"spatialJitter":0,"x":1724,"y":340,"w":644,"h":404,"spawn_time":1555011896389.91},{"trial":33,"type":"Target","inducers":16,"orientationJitter":0.01111111,"spatialJitter":0,"x":1276,"y":1284,"w":444,"h":628,"spawn_time":1555011899118.65},{"trial":34,"type":"Target","inducers":16,"orientationJitter":0.01111111,"spatialJitter":0,"x":1456,"y":128,"w":468,"h":620,"spawn_time":1555011901627.58},{"trial":35,"type":"Target","inducers":16,"orientationJitter":0.01111111,"spatialJitter":0,"x":700,"y":900,"w":612,"h":484,"spawn_time":1555011904236.18},{"trial":36,"type":"Target","inducers":16,"orientationJitter":0.02222222,"spatialJitter":0,"x":1124,"y":956,"w":604,"h":500,"spawn_time":1555011907216.58},{"trial":37,"type":"Target","inducers":16,"orientationJitter":0.02222222,"spatialJitter":0,"x":1452,"y":1108,"w":644,"h":420,"spawn_time":1555011909359.08},{"trial":38,"type":"Target","inducers":16,"orientationJitter":0.02222222,"spatialJitter":0,"x":468,"y":992,"w":636,"h":428,"spawn_time":1555011911729.99},{"trial":39,"type":"Target","inducers":16,"orientationJitter":0.01111111,"spatialJitter":0,"x":1768,"y":188,"w":620,"h":468,"spawn_time":1555011915350.54},{"trial":40,"type":"Target","inducers":16,"orientationJitter":0.01111111,"spatialJitter":0,"x":216,"y":864,"w":652,"h":356,"spawn_time":1555011917863.75},{"trial":41,"type":"Target","inducers":16,"orientationJitter":0,"spatialJitter":0,"x":1008,"y":1332,"w":572,"h":532,"spawn_time":1555011920069.99},{"trial":42,"type":"Target","inducers":16,"orientationJitter":0,"spatialJitter":0,"x":96,"y":924,"w":572,"h":532,"spawn_time":1555011922319.97},{"trial":43,"type":"Target","inducers":16,"orientationJitter":0,"spatialJitter":0,"x":448,"y":864,"w":388,"h":652,"spawn_time":1555011924487.34},{"trial":44,"type":"Target","inducers":16,"orientationJitter":0,"spatialJitter":0,"x":1928,"y":1252,"w":396,"h":644,"spawn_time":1555011927173.78},{"trial":45,"type":"Target","inducers":16,"orientationJitter":0,"spatialJitter":0,"x":292,"y":88,"w":500,"h":604,"spawn_time":1555011929179.62},{"trial":46,"type":"Target","inducers":16,"orientationJitter":0,"spatialJitter":0,"x":812,"y":520,"w":620,"h":468,"spawn_time":1555011931330.37},{"trial":47,"type":"Target","inducers":16,"orientationJitter":0,"spatialJitter":0,"x":344,"y":720,"w":412,"h":644,"spawn_time":1555011933380.6},{"trial":48,"type":"Target","inducers":16,"orientationJitter":0.01111111,"spatialJitter":0,"x":1096,"y":464,"w":588,"h":516,"spawn_time":1555011935581.14},{"trial":49,"type":"Target","inducers":16,"orientationJitter":0.01111111,"spatialJitter":0,"x":1676,"y":128,"w":348,"h":652,"spawn_time":1555011937714.6},{"trial":50,"type":"Target","inducers":16,"orientationJitter":0,"spatialJitter":0,"x":296,"y":956,"w":596,"h":508,"spawn_time":1555011940292.83},{"trial":51,"type":"Target","inducers":16,"orientationJitter":0,"spatialJitter":0,"x":932,"y":816,"w":444,"h":628,"spawn_time":1555011942532.51},{"trial":52,"type":"Target","inducers":16,"orientationJitter":0,"spatialJitter":0,"x":1676,"y":504,"w":508,"h":596,"spawn_time":1555011944944.42},{"trial":53,"type":"Target","inducers":16,"orientationJitter":0,"spatialJitter":0,"x":164,"y":592,"w":612,"h":476,"spawn_time":1555011947274.72},{"trial":54,"type":"Target","inducers":16,"orientationJitter":0,"spatialJitter":0,"x":1104,"y":320,"w":588,"h":516,"spawn_time":1555011949466.87},{"trial":55,"type":"Target","inducers":16,"orientationJitter":0,"spatialJitter":0,"x":228,"y":920,"w":612,"h":484,"spawn_time":1555011952408.52}]}